asdk_plugin_portfolio_management/__init__.py
asdk_plugin_portfolio_management/api_registry.py
asdk_plugin_portfolio_management/domain_apis_list.json
asdk_plugin_portfolio_management/agraph/__init__.py
asdk_plugin_portfolio_management/agraph/portfolio_management/__init__.py
asdk_plugin_portfolio_management/agraph/portfolio_management/cash/__init__.py
asdk_plugin_portfolio_management/agraph/portfolio_management/cash/cash_ladder/__init__.py
asdk_plugin_portfolio_management/agraph/portfolio_management/cash/cash_ladder/v2/__init__.py
asdk_plugin_portfolio_management/agraph/portfolio_management/cash/cash_ladder/v2/CashLadderAPI/__init__.py
asdk_plugin_portfolio_management/agraph/portfolio_management/cash/cash_ladder/v2/CashLadderAPI/api_client.py
asdk_plugin_portfolio_management/agraph/portfolio_management/cash/cash_ladder/v2/CashLadderAPI/api_response.py
asdk_plugin_portfolio_management/agraph/portfolio_management/cash/cash_ladder/v2/CashLadderAPI/configuration.py
asdk_plugin_portfolio_management/agraph/portfolio_management/cash/cash_ladder/v2/CashLadderAPI/exceptions.py
asdk_plugin_portfolio_management/agraph/portfolio_management/cash/cash_ladder/v2/CashLadderAPI/rest.py
asdk_plugin_portfolio_management/agraph/portfolio_management/cash/cash_ladder/v2/CashLadderAPI/swagger.json
asdk_plugin_portfolio_management/agraph/portfolio_management/cash/cash_ladder/v2/CashLadderAPI/api/__init__.py
asdk_plugin_portfolio_management/agraph/portfolio_management/cash/cash_ladder/v2/CashLadderAPI/api/default_cash_ladder_api.py
asdk_plugin_portfolio_management/agraph/portfolio_management/cash/cash_ladder/v2/CashLadderAPI/models/__init__.py
asdk_plugin_portfolio_management/agraph/portfolio_management/cash/cash_ladder/v2/CashLadderAPI/models/any.py
asdk_plugin_portfolio_management/agraph/portfolio_management/cash/cash_ladder/v2/CashLadderAPI/models/cash_ladder_api_get_cash_ladder400_response.py
asdk_plugin_portfolio_management-2.0.0b2.dist-info/METADATA
asdk_plugin_portfolio_management-2.0.0b2.dist-info/WHEEL
asdk_plugin_portfolio_management-2.0.0b2.dist-info/top_level.txt
asdk_plugin_portfolio_management-2.0.0b2.dist-info/RECORD
